udefect/__init__.py
udefect/io/vasp/inputs.py
udefect/udefect.py
udefect-0.0.1.dist-info/METADATA
udefect-0.0.1.dist-info/WHEEL
udefect-0.0.1.dist-info/RECORD
