Metadata-Version: 2.1
Name: udefect
Version: 0.0.1
Summary: A unified first principle defect calculaiton framework
Home-page: https://github.com/Shibu778/udefect
License: MIT
Keywords: defect,udefect,transition level,ZPL,ZFS
Author: Shibu Meher
Author-email: shibumeher@iisc.ac.in
Requires-Python: >=3.11,<4.0
Classifier: License :: OSI Approved :: MIT License
Classifier: Operating System :: OS Independent
Classifier: Programming Language :: Python :: 3
Classifier: Programming Language :: Python :: 3.11
Classifier: Programming Language :: Python :: 3.10
Classifier: Programming Language :: Python :: 3.6
Classifier: Programming Language :: Python :: 3.7
Classifier: Programming Language :: Python :: 3.8
Classifier: Programming Language :: Python :: 3.9
Requires-Dist: pytest (>=8.1.1,<9.0.0)
Project-URL: Repository, https://github.com/Shibu778/udefect
